ckeditor_link/__init__.py
ckeditor_link/admin.py
ckeditor_link/conf.py
ckeditor_link/link_model/__init__.py
ckeditor_link/link_model/conf.py
ckeditor_link/link_model/models.py
ckeditor_link/management/__init__.py
ckeditor_link/management/commands/__init__.py
ckeditor_link/management/commands/cmsplugin2ckeditor_link.py
ckeditor_link/static/admin/ckeditor_link/css/link_admin.css
ckeditor_link/static/ckeditor/ckeditor/plugins/djangolink/plugin.js
ckeditor_link/static/ckeditor/ckeditor/plugins/djangolink/dialogs/djangolink.js
ckeditor_link/static/ckeditor/ckeditor/plugins/djangolink/examples-not-used/ckeditor_original_link_dialog.js
ckeditor_link/static/ckeditor/ckeditor/plugins/djangolink/examples-not-used/ckeditor_original_link_plugin.js
ckeditor_link/static/ckeditor/ckeditor/plugins/djangolink/examples-not-used/cmsplugin_example.js
ckeditor_link/static/djangocms_text_ckeditor/ckeditor/plugins/djangolink/plugin.js
ckeditor_link/static/djangocms_text_ckeditor/ckeditor/plugins/djangolink/dialogs/djangolink.js
ckeditor_link/static/djangocms_text_ckeditor/ckeditor/plugins/djangolink/examples-not-used/ckeditor_original_link_dialog.js
ckeditor_link/static/djangocms_text_ckeditor/ckeditor/plugins/djangolink/examples-not-used/ckeditor_original_link_plugin.js
ckeditor_link/static/djangocms_text_ckeditor/ckeditor/plugins/djangolink/examples-not-used/cmsplugin_example.js
ckeditor_link/templatetags/__init__.py
ckeditor_link/templatetags/ckeditor_link_tags.py
ckeditor_link/tests/__init__.py
ckeditor_link/tests/settings.py
ckeditor_link/tests/settings_no_headless.py
ckeditor_link/tests/test_editor.py
ckeditor_link/tests/test_link_model.py
ckeditor_link/tests/test_templatetag.py
ckeditor_link/tests/urls.py
ckeditor_link/tests/test_app/__init__.py
ckeditor_link/tests/test_app/admin.py
ckeditor_link/tests/test_app/models.py
ckeditor_link/tests/test_app/views.py
ckeditor_link/tests/test_app/migrations/0001_initial.py
ckeditor_link/tests/test_app/migrations/0002_auto_20161128_1458.py
django_ckeditor_link-0.5.3.dist-info/LICENSE
django_ckeditor_link-0.5.3.dist-info/METADATA
django_ckeditor_link-0.5.3.dist-info/WHEEL
django_ckeditor_link-0.5.3.dist-info/top_level.txt
django_ckeditor_link-0.5.3.dist-info/RECORD
