Metadata-Version: 2.1
Name: django-ckeditor-link
Version: 0.5.3
Summary: Alternative link dialog for ckeditor 4, using django modeladmin forms.
Home-page: http://github.com/bnzk/django-ckeditor-link
Author: Ben Stähli
Author-email: bnzk@bnzk.ch
License: MIT
Platform: OS Independent
Classifier: Development Status :: 4 - Beta
Classifier: Framework :: Django
Classifier: Intended Audience :: Developers
Classifier: License :: OSI Approved :: MIT License
Classifier: Operating System :: OS Independent
Classifier: Programming Language :: Python
Classifier: Topic :: Internet :: WWW/HTTP
License-File: LICENSE
Requires-Dist: Django >=1.11
